shy_tools/__init__.py
shy_tools/base_class.py
shy_tools/base_utils.py
shy_tools/data_transform.py
shy_tools/data_visualization.py
shy_tools/database_connect.py
shy_tools/feature_generate.py
shy_tools/feature_select.py
shy_tools/model.py
shy_tools/model_ensemble.py
shy_tools/param_optimize.py
shy_tools/pipline.py
shy_tools-0.0.9.dist-info/LICENSE
shy_tools-0.0.9.dist-info/METADATA
shy_tools-0.0.9.dist-info/WHEEL
shy_tools-0.0.9.dist-info/top_level.txt
shy_tools-0.0.9.dist-info/RECORD
