Metadata-Version: 2.1
Name: shy-tools
Version: 0.0.9
Summary: My code tools
Home-page: https://github.com/smileshy777/shy_tools
Author: shy
Author-email: 13141462249@163.com
License: UNKNOWN
Platform: UNKNOWN
